imgutils/__init__.py
imgutils/__main__.py
gi_imgutils-0.0.1a0.dist-info/LICENSE
gi_imgutils-0.0.1a0.dist-info/METADATA
gi_imgutils-0.0.1a0.dist-info/WHEEL
gi_imgutils-0.0.1a0.dist-info/entry_points.txt
gi_imgutils-0.0.1a0.dist-info/top_level.txt
gi_imgutils-0.0.1a0.dist-info/RECORD
